docs/custom_makefiles.md
docs/index.md
docs/user_guide.md
src/mcp_server_make/__init__.py
src/mcp_server_make/__main__.py
src/mcp_server_make/server.py
tests/test_server.py
orange_mcp_server_make-0.3.1.dist-info/METADATA
orange_mcp_server_make-0.3.1.dist-info/WHEEL
orange_mcp_server_make-0.3.1.dist-info/entry_points.txt
orange_mcp_server_make-0.3.1.dist-info/licenses/LICENSE
orange_mcp_server_make-0.3.1.dist-info/RECORD
