Metadata-Version: 2.4
Name: orange-mcp-server-make
Version: 0.3.1
Summary: A Model Context Protocol server providing access to make functionality
Author-email: "Joshua M. Dotson" <contact@jmdots.com>
Maintainer-email: "Joshua M. Dotson" <contact@jmdots.com>
License: MIT
License-File: LICENSE
Keywords: automation,llm,make,mcp
Classifier: Development Status :: 4 - Beta
Classifier: Intended Audience :: Developers
Classifier: License :: OSI Approved :: MIT License
Classifier: Programming Language :: Python :: 3
Classifier: Programming Language :: Python :: 3.10
Requires-Python: >=3.10
Requires-Dist: mcp>=1.0.0
Requires-Dist: pydantic>=2.0.0
Provides-Extra: dev
Requires-Dist: mypy>=1.8.0; extra == 'dev'
Requires-Dist: pyright>=1.1.389; extra == 'dev'
Requires-Dist: pytest-asyncio>=0.23.0; extra == 'dev'
Requires-Dist: pytest-cov>=4.1.0; extra == 'dev'
Requires-Dist: pytest>=8.0.0; extra == 'dev'
Requires-Dist: ruff>=0.7.3; extra == 'dev'
Requires-Dist: types-setuptools>=69.0.0; extra == 'dev'
